pybluecat/__init__.py
pybluecat/bam.py
pybluecat/example.py
pybluecat/exceptions.py
pybluecat/data/__init__.py
pybluecat/data/const.py
pybluecat/data/defs.py
pybluecat/data/helpers.py
pybluecat/tools/__init__.py
pybluecat/tools/cli.py
pybluecat/tools/enumerate_networks.py
pybluecat/tools/mac.py
pybluecat/tools/rundeck_dhcp_bulk_request.py
pybluecat/tools/rundeck_dhcp_delete.py
pybluecat/tools/rundeck_dhcp_request.py
pybluecat/tools/rundeck_dhcp_search.py
pybluecat/tools/rundeck_dhcp_update.py
pybluecat/tools/search.py
pybluecat/tools/static_pair_request.py
pybluecat/tools/static_request.py
pybluecat-0.1.1.dist-info/DESCRIPTION.rst
pybluecat-0.1.1.dist-info/METADATA
pybluecat-0.1.1.dist-info/RECORD
pybluecat-0.1.1.dist-info/WHEEL
pybluecat-0.1.1.dist-info/entry_points.txt
pybluecat-0.1.1.dist-info/metadata.json
pybluecat-0.1.1.dist-info/top_level.txt
