Metadata-Version: 2.0
Name: pybluecat
Version: 0.1.1
Summary: Python wrapper around Bluecat APIs
Home-page: https://github.com/ForrestT/pyBluecat
Author: Forrest Throesch
Author-email: fmthroesch@gmail.com
License: Freely Distributable
Platform: UNKNOWN
Classifier: Development Status :: 3 - Alpha
Classifier: Programming Language :: Python :: 2.7
Classifier: Programming Language :: Python :: 3.6
Classifier: License :: Freely Distributable
Classifier: Natural Language :: English
Requires-Dist: dnspython
